masterprograming/PyBasic.py
masterprograming/__init__.py
masterprograming/banking.py
masterprograming/calgui.py
masterprograming/keyboard.py
masterprograming/master.py
masterprograming/notepad.py
masterprograming/pnrgui.py
masterprograming/quiz.py
masterprograming/sciencecal.py
masterprograming/test.py
masterprograming/tkintersimplegui.py
masterprograming/todogui.py
masterprograming-0.0.7.dist-info/LICENSE.txt
masterprograming-0.0.7.dist-info/METADATA
masterprograming-0.0.7.dist-info/WHEEL
masterprograming-0.0.7.dist-info/top_level.txt
masterprograming-0.0.7.dist-info/RECORD
