Metadata-Version: 2.1
Name: masterprograming
Version: 0.0.7
Summary: Master Programing is a PIP Package that enables people that aren’t well to Build Software By Coding And its provides already Build Software 
Home-page: UNKNOWN
Author: Danish Ali
Author-email: help@masterprograming.com
License: UNKNOWN
Platform: UNKNOWN
Classifier: Development Status :: 5 - Production/Stable
Classifier: Intended Audience :: Education
Classifier: Operating System :: Microsoft :: Windows :: Windows 10
Classifier: License :: OSI Approved :: MIT License
Classifier: Programming Language :: Python :: 3
Requires-Python: >=3.6
